openbb_intrinio/__init__.py
openbb_intrinio/models/__init__.py
openbb_intrinio/models/balance_sheet.py
openbb_intrinio/models/calendar_ipo.py
openbb_intrinio/models/cash_flow.py
openbb_intrinio/models/company_filings.py
openbb_intrinio/models/company_news.py
openbb_intrinio/models/currency_pairs.py
openbb_intrinio/models/equity_historical.py
openbb_intrinio/models/equity_info.py
openbb_intrinio/models/equity_quote.py
openbb_intrinio/models/equity_search.py
openbb_intrinio/models/etf_holdings.py
openbb_intrinio/models/etf_info.py
openbb_intrinio/models/etf_price_performance.py
openbb_intrinio/models/etf_search.py
openbb_intrinio/models/financial_attributes.py
openbb_intrinio/models/financial_ratios.py
openbb_intrinio/models/forward_ebitda_estimates.py
openbb_intrinio/models/forward_eps_estimates.py
openbb_intrinio/models/forward_pe_estimates.py
openbb_intrinio/models/forward_sales_estimates.py
openbb_intrinio/models/fred_series.py
openbb_intrinio/models/historical_attributes.py
openbb_intrinio/models/historical_dividends.py
openbb_intrinio/models/historical_market_cap.py
openbb_intrinio/models/income_statement.py
openbb_intrinio/models/index_historical.py
openbb_intrinio/models/insider_trading.py
openbb_intrinio/models/institutional_ownership.py
openbb_intrinio/models/key_metrics.py
openbb_intrinio/models/latest_attributes.py
openbb_intrinio/models/market_snapshots.py
openbb_intrinio/models/options_chains.py
openbb_intrinio/models/options_snapshots.py
openbb_intrinio/models/options_unusual.py
openbb_intrinio/models/price_target_consensus.py
openbb_intrinio/models/reported_financials.py
openbb_intrinio/models/search_attributes.py
openbb_intrinio/models/share_statistics.py
openbb_intrinio/models/world_news.py
openbb_intrinio/py.typed
openbb_intrinio/utils/__init__.py
openbb_intrinio/utils/helpers.py
openbb_intrinio/utils/references.py
openbb_intrinio-1.4.1.dist-info/METADATA
openbb_intrinio-1.4.1.dist-info/WHEEL
openbb_intrinio-1.4.1.dist-info/entry_points.txt
openbb_intrinio-1.4.1.dist-info/RECORD
